gdbfs/__init__.py
gdbfs/sfs.py
gdbfs-0.2.dist-info/METADATA
gdbfs-0.2.dist-info/WHEEL
gdbfs-0.2.dist-info/top_level.txt
gdbfs-0.2.dist-info/RECORD
